[{
  "slug": "Line/Range(Analysis) Chart",
  "name": "Line/Range(Analysis) Chart",
  "image": "linerangechart.png",
  "url": "https://rgabs.github.io/lineRangeChart/",
  "date": "July 2016",
  "tags": ["jQuery", "CSS", "HTML"]
}, {
  "slug": "Matrix Chart",
  "name": "Matrix Chart",
  "image": "matrix.png",
  "url": "http://rgabs.github.io/matrixChart/",
  "date": "Jan 2016",
  "tags": ["jQuery", "CSS", "HTML"]
}, {
  "slug": "Searchable Select Dropdown",
  "name": "Searchable Select Dropdown",
  "image": "dropdown.png",
  "url": "https://rgabs.github.io/searchable-select-dropdown/",
  "date": "June 2016",
  "tags": ["VueJS", "NPM"]
}, {
  "slug": "noUISlider Directive",
  "name": "noUISlider Directive",
  "image": "nouislider.png",
  "url": "https://rgabs.github.io/2016/01/06/es6-based-angular-directive-for.html",
  "date": "Jan 2016",
  "tags": ["AngularJS", "ES6", "CSS"]
}, {
  "slug": "iPhoneInstallOverlay",
  "name": "iPhoneInstallOverlay Plugin",
  "image": "iphoneoverlay.png",
  "url": "http://rahulgaba.com/front-end/2016/07/31/Showing-add-to-homescreen-banner-in-iPhone-Safari.html",
  "date": "Aug 2016",
  "tags": ["NPM", "Bower", "CSS", "HTML"]
}, {
  "slug": "expediaVR",
  "name": "expediaVR",
  "image": "expediavr.png",
  "url": "http://tinyurl.com/expediavr",
  "date": "Sept 2016",
  "tags": ["Aframe", "Web-VR"]
}, {
  "slug": "Facet Directive",
  "name": "Facet Directive",
  "image": "facet.png",
  "url": "http://rahulgaba.com/facet-directive/",
  "date": "October 2016",
  "tags": ["Bower", "AngularJS"]
}]
